sdk/tokencut/__init__.py
sdk/tokencut/client.py
tokencut-0.1.4.dist-info/METADATA
tokencut-0.1.4.dist-info/WHEEL
tokencut-0.1.4.dist-info/top_level.txt
tokencut-0.1.4.dist-info/RECORD
